pypkgs_lhabashy/__init__.py
pypkgs_lhabashy/pypkgs_lhabashy.py
pypkgs_lhabashy-0.1.0.dist-info/LICENSE
pypkgs_lhabashy-0.1.0.dist-info/WHEEL
pypkgs_lhabashy-0.1.0.dist-info/METADATA
pypkgs_lhabashy-0.1.0.dist-info/RECORD
