Metadata-Version: 2.1
Name: pypkgs-lhabashy
Version: 0.1.0
Summary: Python package for assignment 1
License: MIT
Author: larahabashy
Author-email: laraahabashy@gmail.com
Requires-Python: >=3.7.1,<4.0
Classifier: License :: OSI Approved :: MIT License
Classifier: Programming Language :: Python :: 3
Classifier: Programming Language :: Python :: 3.8
Classifier: Programming Language :: Python :: 3.9
Requires-Dist: pandas (>=1.2.2,<2.0.0)
